TonicPublisherAPI/__init__.py
TonicPublisherAPI-0.2.dist-info/METADATA
TonicPublisherAPI-0.2.dist-info/WHEEL
TonicPublisherAPI-0.2.dist-info/top_level.txt
TonicPublisherAPI-0.2.dist-info/RECORD
