Metadata-Version: 2.1
Name: TonicPublisherAPI
Version: 0.2
Summary: Async API wrapper for Tonic.com Publisher API v3
Requires-Dist: aiohttp >=3.8.5
Requires-Dist: aiodns >=3.0.0
